object_model/__init__.py
object_model/_dataclasses.py
object_model/_descriptors.py
object_model/_json.py
object_model/_pydantic.py
object_model/_replace.py
object_model/_type_checking.py
object_model/_type_registry.py
object_model/store/__init__.py
object_model/store/exception.py
object_model/store/object_record.py
object_model/store/object_result.py
object_model/store/object_store.py
object_model/store/persistable.py
object_model/store/sql_store.py
object_model/store/union_store.py
object_model/store/web_client.py
object_model/store/web_server.py
object_model/test/__init__.py
object_model/test/shared_dataclass_types.py
object_model/test/shared_pydantic_types.py
object_model/test/test_dataclass_serialisation.py
object_model/test/test_id.py
object_model/test/test_json_schema_validation.py
object_model/test/test_persistence.py
object_model/test/test_pydantic_serialisation.py
object_model/test/test_replace.py
py_object_model-1.0.0.dist-info/LICENSE
py_object_model-1.0.0.dist-info/METADATA
py_object_model-1.0.0.dist-info/WHEEL
py_object_model-1.0.0.dist-info/entry_points.txt
py_object_model-1.0.0.dist-info/top_level.txt
py_object_model-1.0.0.dist-info/RECORD
