Metadata-Version: 2.1
Name: py-object-model
Version: 1.0.0
Summary: Core Object Model
Author-email: Nick Young <nick.young.github@gmail.com>
License: MIT License
Project-URL: homepage, https://github.com/nickyoung-github/object-model
Classifier: License :: OSI Approved :: MIT License
Classifier: Programming Language :: Python :: 3
Classifier: Programming Language :: Python :: 3 :: Only
Classifier: Programming Language :: Python :: 3.11
Classifier: Programming Language :: Python :: 3.12
Classifier: Programming Language :: Python :: 3.13
Classifier: Operating System :: OS Independent
Requires-Python: >=3.11
License-File: LICENSE
Requires-Dist: fastapi
Requires-Dist: frozendict
Requires-Dist: jsonschema
Requires-Dist: orjson
Requires-Dist: psycopg
Requires-Dist: pydantic
Requires-Dist: pydantic_gubbins
Requires-Dist: pywin32; platform_system == "Windows"
Requires-Dist: requests
Requires-Dist: setuptools
Requires-Dist: sqlalchemy
Requires-Dist: sqlalchemy-utc
Requires-Dist: sqlmodel
Requires-Dist: uvicorn
Provides-Extra: test
Requires-Dist: pytest; extra == "test"
Requires-Dist: pytest-cov; extra == "test"
